deescovery/__init__.py
deescovery/contrib.py
deescovery/discovery.py
deescovery/flask.py
deescovery/helpers.py
deescovery/matchers.py
deescovery-1.1.0.dist-info/LICENSE
deescovery-1.1.0.dist-info/WHEEL
deescovery-1.1.0.dist-info/METADATA
deescovery-1.1.0.dist-info/RECORD
