Metadata-Version: 2.1
Name: deescovery
Version: 1.1.0
Summary: Discover packages and classes in a python project.
Home-page: https://github.com/imankulov/deescovery
License: MIT
Author: Roman Imankulov
Author-email: roman.imankulov@gmail.com
Requires-Python: >=3.7.8,<4.0
Classifier: Development Status :: 4 - Beta
Classifier: Intended Audience :: Developers
Classifier: License :: OSI Approved :: MIT License
Classifier: Natural Language :: English
Classifier: Programming Language :: Python :: 3
Classifier: Programming Language :: Python :: 3.10
Classifier: Programming Language :: Python :: 3.7
Classifier: Programming Language :: Python :: 3.8
Classifier: Programming Language :: Python :: 3.9
